[
    {
        "index": 0,
        "timestamp": 1777701769.2062428,
        "data": "Genesis Block - NexusGuard Ledger Initialized",
        "previous_hash": "0",
        "hash": "f1ad93fbe863a7bdb22d69dc1206d41ab9a4e38c2fde18016b2716c32319292f"
    },
    {
        "index": 1,
        "timestamp": 1777701999.2113101,
        "data": {
            "type": "ALERT",
            "alert_id": "0f3682b5-de53-41f3-8e7b-ac2bd2030bea",
            "endpoint_id": "SachinChauhan",
            "timestamp": 1777701995.0579753,
            "risk_level": "Medium",
            "details": {
                "risk_level": "Medium",
                "description": "Unknown Process Executed: notepad.exe",
                "destination_ip": "N/A",
                "process_name": "notepad.exe",
                "metrics": "CPU: 34.1% | Mem: 86.2% | Net Tx: 0.0023MB/s",
                "root_cause": "A benign-looking application was started that has never been used by this user.",
                "remediation": "1. Verify if 'notepad.exe' is company-approved. 2. Monitor for further anomalous actions.",
                "frequency": 1,
                "source_ip": "127.0.0.1"
            }
        },
        "previous_hash": "f1ad93fbe863a7bdb22d69dc1206d41ab9a4e38c2fde18016b2716c32319292f",
        "hash": "a3b946cdcdc548aab4a6bc1a7bfe99244d0e616ed6f58602cd79a68e521b35f0"
    },
    {
        "index": 2,
        "timestamp": 1777702001.2318616,
        "data": {
            "type": "ALERT",
            "alert_id": "538540fb-1b2f-4ff8-b263-4ea383da6e58",
            "endpoint_id": "SachinChauhan",
            "timestamp": 1777701995.0579753,
            "risk_level": "Low",
            "details": {
                "risk_level": "Low",
                "description": "Irregular Website/IP Usage",
                "destination_ip": "2600:1417:56:185::57",
                "process_name": "Unknown",
                "metrics": "CPU: 34.1% | Mem: 86.2% | Net Tx: 0.0023MB/s",
                "root_cause": "Endpoint navigated to an IP that is not in its historical baseline.",
                "remediation": "1. Log IP 2600:1417:56:185::57 for threat intel correlation. 2. No immediate action required.",
                "frequency": 1,
                "source_ip": "127.0.0.1"
            }
        },
        "previous_hash": "a3b946cdcdc548aab4a6bc1a7bfe99244d0e616ed6f58602cd79a68e521b35f0",
        "hash": "729ecdecea1223985050984bf614a98da77fc830a5439ab20eace721884124fb"
    },
    {
        "index": 3,
        "timestamp": 1777702003.2465572,
        "data": {
            "type": "ALERT",
            "alert_id": "b33b5185-9a6e-4e8e-893b-483a647f33b1",
            "endpoint_id": "SachinChauhan",
            "timestamp": 1777701995.0579753,
            "risk_level": "Low",
            "details": {
                "risk_level": "Low",
                "description": "Irregular Website/IP Usage",
                "destination_ip": "2600:1417:56:289::3114",
                "process_name": "Unknown",
                "metrics": "CPU: 34.1% | Mem: 86.2% | Net Tx: 0.0023MB/s",
                "root_cause": "Endpoint navigated to an IP that is not in its historical baseline.",
                "remediation": "1. Log IP 2600:1417:56:289::3114 for threat intel correlation. 2. No immediate action required.",
                "frequency": 2,
                "source_ip": "127.0.0.1"
            }
        },
        "previous_hash": "729ecdecea1223985050984bf614a98da77fc830a5439ab20eace721884124fb",
        "hash": "e57b23751fa8b663bfb541c1ac864156bdc635240404bbfaa44fe2bcee051035"
    },
    {
        "index": 4,
        "timestamp": 1777702012.4141228,
        "data": {
            "type": "ALERT",
            "alert_id": "66fe7b22-53cf-4090-bb36-611945038793",
            "endpoint_id": "SachinChauhan",
            "timestamp": 1777702008.2821617,
            "risk_level": "Medium",
            "details": {
                "risk_level": "Medium",
                "description": "Unknown Process Executed: notepad.exe",
                "destination_ip": "N/A",
                "process_name": "notepad.exe",
                "metrics": "CPU: 15.9% | Mem: 87.0% | Net Tx: 0.0008MB/s",
                "root_cause": "A benign-looking application was started that has never been used by this user.",
                "remediation": "1. Verify if 'notepad.exe' is company-approved. 2. Monitor for further anomalous actions.",
                "frequency": 2,
                "source_ip": "127.0.0.1"
            }
        },
        "previous_hash": "e57b23751fa8b663bfb541c1ac864156bdc635240404bbfaa44fe2bcee051035",
        "hash": "828c8d77b8885bc2a7225fb56fdb72a7c725ce21038d4b47ec4726a086ee40f1"
    },
    {
        "index": 5,
        "timestamp": 1777702014.4450772,
        "data": {
            "type": "ALERT",
            "alert_id": "fa3f4613-3613-48b1-998f-0435b4d76c3a",
            "endpoint_id": "SachinChauhan",
            "timestamp": 1777702008.2821617,
            "risk_level": "Low",
            "details": {
                "risk_level": "Low",
                "description": "Irregular Website/IP Usage",
                "destination_ip": "2600:1417:56:185::57",
                "process_name": "Unknown",
                "metrics": "CPU: 15.9% | Mem: 87.0% | Net Tx: 0.0008MB/s",
                "root_cause": "Endpoint navigated to an IP that is not in its historical baseline.",
                "remediation": "1. Log IP 2600:1417:56:185::57 for threat intel correlation. 2. No immediate action required.",
                "frequency": 3,
                "source_ip": "127.0.0.1"
            }
        },
        "previous_hash": "828c8d77b8885bc2a7225fb56fdb72a7c725ce21038d4b47ec4726a086ee40f1",
        "hash": "a2408b6077a123c669f99869a9d4dd4041aa1588e687b6993aa4c568e1064558"
    },
    {
        "index": 6,
        "timestamp": 1777702016.4705172,
        "data": {
            "type": "ALERT",
            "alert_id": "273c927f-873e-4e86-ad46-68e53508106c",
            "endpoint_id": "SachinChauhan",
            "timestamp": 1777702008.2821617,
            "risk_level": "Low",
            "details": {
                "risk_level": "Low",
                "description": "Irregular Website/IP Usage",
                "destination_ip": "40.126.18.32",
                "process_name": "Unknown",
                "metrics": "CPU: 15.9% | Mem: 87.0% | Net Tx: 0.0008MB/s",
                "root_cause": "Endpoint navigated to an IP that is not in its historical baseline.",
                "remediation": "1. Log IP 40.126.18.32 for threat intel correlation. 2. No immediate action required.",
                "frequency": 4,
                "source_ip": "127.0.0.1"
            }
        },
        "previous_hash": "a2408b6077a123c669f99869a9d4dd4041aa1588e687b6993aa4c568e1064558",
        "hash": "9cef867065480fe422081b955943142b7e0e0fa0bed588a7bb04e650b0ba9f64"
    },
    {
        "index": 7,
        "timestamp": 1777702018.500174,
        "data": {
            "type": "ALERT",
            "alert_id": "79d99d3b-d9d6-4902-bf17-79e3b5cc8bc4",
            "endpoint_id": "SachinChauhan",
            "timestamp": 1777702008.2821617,
            "risk_level": "Low",
            "details": {
                "risk_level": "Low",
                "description": "Irregular Website/IP Usage",
                "destination_ip": "2600:1417:56:289::3114",
                "process_name": "Unknown",
                "metrics": "CPU: 15.9% | Mem: 87.0% | Net Tx: 0.0008MB/s",
                "root_cause": "Endpoint navigated to an IP that is not in its historical baseline.",
                "remediation": "1. Log IP 2600:1417:56:289::3114 for threat intel correlation. 2. No immediate action required.",
                "frequency": 5,
                "source_ip": "127.0.0.1"
            }
        },
        "previous_hash": "9cef867065480fe422081b955943142b7e0e0fa0bed588a7bb04e650b0ba9f64",
        "hash": "ce3a1d4e008df73558891ba6995cf2a1885f6253401a1b5ba88f9dbedde839e2"
    },
    {
        "index": 8,
        "timestamp": 1777702027.477621,
        "data": {
            "type": "ALERT",
            "alert_id": "7ba6ba05-a311-47cf-9d0d-e8f8790afd5c",
            "endpoint_id": "SachinChauhan",
            "timestamp": 1777702023.3588145,
            "risk_level": "Medium",
            "details": {
                "risk_level": "Medium",
                "description": "Unknown Process Executed: notepad.exe",
                "destination_ip": "N/A",
                "process_name": "notepad.exe",
                "metrics": "CPU: 17.1% | Mem: 87.9% | Net Tx: 0.0003MB/s",
                "root_cause": "A benign-looking application was started that has never been used by this user.",
                "remediation": "1. Verify if 'notepad.exe' is company-approved. 2. Monitor for further anomalous actions.",
                "frequency": 3,
                "source_ip": "127.0.0.1"
            }
        },
        "previous_hash": "ce3a1d4e008df73558891ba6995cf2a1885f6253401a1b5ba88f9dbedde839e2",
        "hash": "a72073a7e1524d4d9d7de1131410e936c03d2b8bb497868191f2fe92a7b7d4f0"
    },
    {
        "index": 9,
        "timestamp": 1777702029.514386,
        "data": {
            "type": "ALERT",
            "alert_id": "aaae4ffa-08de-4753-8e63-0739ef09437d",
            "endpoint_id": "SachinChauhan",
            "timestamp": 1777702023.3588145,
            "risk_level": "Low",
            "details": {
                "risk_level": "Low",
                "description": "Irregular Website/IP Usage",
                "destination_ip": "2600:1417:56:185::57",
                "process_name": "Unknown",
                "metrics": "CPU: 17.1% | Mem: 87.9% | Net Tx: 0.0003MB/s",
                "root_cause": "Endpoint navigated to an IP that is not in its historical baseline.",
                "remediation": "1. Log IP 2600:1417:56:185::57 for threat intel correlation. 2. No immediate action required.",
                "frequency": 6,
                "source_ip": "127.0.0.1"
            }
        },
        "previous_hash": "a72073a7e1524d4d9d7de1131410e936c03d2b8bb497868191f2fe92a7b7d4f0",
        "hash": "4e50b40adaa94d77c6da1b079f35977099f99f04c0bf510030559b447ba1f547"
    },
    {
        "index": 10,
        "timestamp": 1777702031.538969,
        "data": {
            "type": "ALERT",
            "alert_id": "f06954d3-d742-442b-b73e-eeb47613718e",
            "endpoint_id": "SachinChauhan",
            "timestamp": 1777702023.3588145,
            "risk_level": "Low",
            "details": {
                "risk_level": "Low",
                "description": "Irregular Website/IP Usage",
                "destination_ip": "40.126.18.32",
                "process_name": "Unknown",
                "metrics": "CPU: 17.1% | Mem: 87.9% | Net Tx: 0.0003MB/s",
                "root_cause": "Endpoint navigated to an IP that is not in its historical baseline.",
                "remediation": "1. Log IP 40.126.18.32 for threat intel correlation. 2. No immediate action required.",
                "frequency": 7,
                "source_ip": "127.0.0.1"
            }
        },
        "previous_hash": "4e50b40adaa94d77c6da1b079f35977099f99f04c0bf510030559b447ba1f547",
        "hash": "3cf30b5d30cef76f7eafb0a374478bc4bccb75426dbe9b040bf3799246a00398"
    },
    {
        "index": 11,
        "timestamp": 1777702033.561774,
        "data": {
            "type": "ALERT",
            "alert_id": "437c7758-8f99-4dd9-968a-a417bd141f7e",
            "endpoint_id": "SachinChauhan",
            "timestamp": 1777702023.3588145,
            "risk_level": "Low",
            "details": {
                "risk_level": "Low",
                "description": "Irregular Website/IP Usage",
                "destination_ip": "2600:1417:56:289::3114",
                "process_name": "Unknown",
                "metrics": "CPU: 17.1% | Mem: 87.9% | Net Tx: 0.0003MB/s",
                "root_cause": "Endpoint navigated to an IP that is not in its historical baseline.",
                "remediation": "1. Log IP 2600:1417:56:289::3114 for threat intel correlation. 2. No immediate action required.",
                "frequency": 8,
                "source_ip": "127.0.0.1"
            }
        },
        "previous_hash": "3cf30b5d30cef76f7eafb0a374478bc4bccb75426dbe9b040bf3799246a00398",
        "hash": "f459889b3524e366237a478ae006a02bd0d8ac37199c93d344ebb42c12312bb9"
    },
    {
        "index": 12,
        "timestamp": 1777702047.595125,
        "data": {
            "type": "ALERT",
            "alert_id": "a550fedb-ab8d-4872-b322-8eb1836fbe98",
            "endpoint_id": "SachinChauhan",
            "timestamp": 1777702043.434027,
            "risk_level": "Low",
            "details": {
                "risk_level": "Low",
                "description": "Irregular Website/IP Usage",
                "destination_ip": "2600:1417:56:185::57",
                "process_name": "Unknown",
                "metrics": "CPU: 16.3% | Mem: 86.6% | Net Tx: 0.0003MB/s",
                "root_cause": "Endpoint navigated to an IP that is not in its historical baseline.",
                "remediation": "1. Log IP 2600:1417:56:185::57 for threat intel correlation. 2. No immediate action required.",
                "frequency": 9,
                "source_ip": "127.0.0.1"
            }
        },
        "previous_hash": "f459889b3524e366237a478ae006a02bd0d8ac37199c93d344ebb42c12312bb9",
        "hash": "12b1abd77ced8d2f3c5c7843712dd2a2da51cd07981b16c5c9dcad1648630036"
    },
    {
        "index": 13,
        "timestamp": 1777702049.6087387,
        "data": {
            "type": "ALERT",
            "alert_id": "c1d5966e-5294-44c3-9bb0-42bbf4de3e00",
            "endpoint_id": "SachinChauhan",
            "timestamp": 1777702043.434027,
            "risk_level": "Low",
            "details": {
                "risk_level": "Low",
                "description": "Irregular Website/IP Usage",
                "destination_ip": "40.126.18.32",
                "process_name": "Unknown",
                "metrics": "CPU: 16.3% | Mem: 86.6% | Net Tx: 0.0003MB/s",
                "root_cause": "Endpoint navigated to an IP that is not in its historical baseline.",
                "remediation": "1. Log IP 40.126.18.32 for threat intel correlation. 2. No immediate action required.",
                "frequency": 10,
                "source_ip": "127.0.0.1"
            }
        },
        "previous_hash": "12b1abd77ced8d2f3c5c7843712dd2a2da51cd07981b16c5c9dcad1648630036",
        "hash": "a78e9dcb843aa3fa3f157da29ddd27b3f6809b3c9cbeda9b454f70503a8d5cd1"
    },
    {
        "index": 14,
        "timestamp": 1777702051.63293,
        "data": {
            "type": "ALERT",
            "alert_id": "04740f98-7ea2-4fd6-86c1-90b3fc35812b",
            "endpoint_id": "SachinChauhan",
            "timestamp": 1777702043.434027,
            "risk_level": "Low",
            "details": {
                "risk_level": "Low",
                "description": "Irregular Website/IP Usage",
                "destination_ip": "2600:1417:56:289::3114",
                "process_name": "Unknown",
                "metrics": "CPU: 16.3% | Mem: 86.6% | Net Tx: 0.0003MB/s",
                "root_cause": "Endpoint navigated to an IP that is not in its historical baseline.",
                "remediation": "1. Log IP 2600:1417:56:289::3114 for threat intel correlation. 2. No immediate action required.",
                "frequency": 11,
                "source_ip": "127.0.0.1"
            }
        },
        "previous_hash": "a78e9dcb843aa3fa3f157da29ddd27b3f6809b3c9cbeda9b454f70503a8d5cd1",
        "hash": "0eb3314bb48bb81f8b1ca9ac4139852eaf826d4d2fea0a67b3e50d8449da364f"
    },
    {
        "index": 15,
        "timestamp": 1777702060.825388,
        "data": {
            "type": "ALERT",
            "alert_id": "44f6127c-0e8c-47e7-9d04-ab87a6ec0a8d",
            "endpoint_id": "SachinChauhan",
            "timestamp": 1777702056.6923444,
            "risk_level": "Low",
            "details": {
                "risk_level": "Low",
                "description": "Irregular Website/IP Usage",
                "destination_ip": "2600:1417:56:185::57",
                "process_name": "Unknown",
                "metrics": "CPU: 11.1% | Mem: 86.4% | Net Tx: 0.0001MB/s",
                "root_cause": "Endpoint navigated to an IP that is not in its historical baseline.",
                "remediation": "1. Log IP 2600:1417:56:185::57 for threat intel correlation. 2. No immediate action required.",
                "frequency": 12,
                "source_ip": "127.0.0.1"
            }
        },
        "previous_hash": "0eb3314bb48bb81f8b1ca9ac4139852eaf826d4d2fea0a67b3e50d8449da364f",
        "hash": "d8f242e8c1829cf76f0bad7ad1f9bcc99918c4b02ce9d9b22a2fd5798e349cf3"
    },
    {
        "index": 16,
        "timestamp": 1777702062.848538,
        "data": {
            "type": "ALERT",
            "alert_id": "22a4675a-06ac-4441-998b-af2c61b12240",
            "endpoint_id": "SachinChauhan",
            "timestamp": 1777702056.6923444,
            "risk_level": "Low",
            "details": {
                "risk_level": "Low",
                "description": "Irregular Website/IP Usage",
                "destination_ip": "40.126.18.32",
                "process_name": "Unknown",
                "metrics": "CPU: 11.1% | Mem: 86.4% | Net Tx: 0.0001MB/s",
                "root_cause": "Endpoint navigated to an IP that is not in its historical baseline.",
                "remediation": "1. Log IP 40.126.18.32 for threat intel correlation. 2. No immediate action required.",
                "frequency": 13,
                "source_ip": "127.0.0.1"
            }
        },
        "previous_hash": "d8f242e8c1829cf76f0bad7ad1f9bcc99918c4b02ce9d9b22a2fd5798e349cf3",
        "hash": "f8853f9f82ed20ab2704984c153ae1bffef272c62241d428b70a608a0c752265"
    },
    {
        "index": 17,
        "timestamp": 1777702064.873474,
        "data": {
            "type": "ALERT",
            "alert_id": "b2572cca-e2c7-40a8-b279-a0d4a1e347ff",
            "endpoint_id": "SachinChauhan",
            "timestamp": 1777702056.6923444,
            "risk_level": "Low",
            "details": {
                "risk_level": "Low",
                "description": "Irregular Website/IP Usage",
                "destination_ip": "2600:1417:56:289::3114",
                "process_name": "Unknown",
                "metrics": "CPU: 11.1% | Mem: 86.4% | Net Tx: 0.0001MB/s",
                "root_cause": "Endpoint navigated to an IP that is not in its historical baseline.",
                "remediation": "1. Log IP 2600:1417:56:289::3114 for threat intel correlation. 2. No immediate action required.",
                "frequency": 14,
                "source_ip": "127.0.0.1"
            }
        },
        "previous_hash": "f8853f9f82ed20ab2704984c153ae1bffef272c62241d428b70a608a0c752265",
        "hash": "c6efc50cd91989216d5af30c22fe5624fbdd4b2b80401b46bc2d25887d249d85"
    },
    {
        "index": 18,
        "timestamp": 1777702074.0684335,
        "data": {
            "type": "ALERT",
            "alert_id": "7a6fc695-bd11-49ca-bc8c-6f0665868a4a",
            "endpoint_id": "SachinChauhan",
            "timestamp": 1777702069.9240668,
            "risk_level": "Low",
            "details": {
                "risk_level": "Low",
                "description": "Irregular Website/IP Usage",
                "destination_ip": "2600:1417:56:185::57",
                "process_name": "Unknown",
                "metrics": "CPU: 18.3% | Mem: 87.3% | Net Tx: 0.0016MB/s",
                "root_cause": "Endpoint navigated to an IP that is not in its historical baseline.",
                "remediation": "1. Log IP 2600:1417:56:185::57 for threat intel correlation. 2. No immediate action required.",
                "frequency": 15,
                "source_ip": "127.0.0.1"
            }
        },
        "previous_hash": "c6efc50cd91989216d5af30c22fe5624fbdd4b2b80401b46bc2d25887d249d85",
        "hash": "0c4f52af5227e76d15578827ee6a178ecfe8a7bd7294f0d6d51a5d830b769a80"
    },
    {
        "index": 19,
        "timestamp": 1777702076.092202,
        "data": {
            "type": "ALERT",
            "alert_id": "7923b325-be38-43eb-8ff3-0c15bce98437",
            "endpoint_id": "SachinChauhan",
            "timestamp": 1777702069.9240668,
            "risk_level": "Low",
            "details": {
                "risk_level": "Low",
                "description": "Irregular Website/IP Usage",
                "destination_ip": "40.126.18.32",
                "process_name": "Unknown",
                "metrics": "CPU: 18.3% | Mem: 87.3% | Net Tx: 0.0016MB/s",
                "root_cause": "Endpoint navigated to an IP that is not in its historical baseline.",
                "remediation": "1. Log IP 40.126.18.32 for threat intel correlation. 2. No immediate action required.",
                "frequency": 16,
                "source_ip": "127.0.0.1"
            }
        },
        "previous_hash": "0c4f52af5227e76d15578827ee6a178ecfe8a7bd7294f0d6d51a5d830b769a80",
        "hash": "137b2e9c97f2a0da58c28009bdb85287a3884efd8ed77d847f2c54bc03356030"
    },
    {
        "index": 20,
        "timestamp": 1777702078.1101813,
        "data": {
            "type": "ALERT",
            "alert_id": "65364d8e-00cc-4c94-b050-53bc82aa8983",
            "endpoint_id": "SachinChauhan",
            "timestamp": 1777702069.9240668,
            "risk_level": "Low",
            "details": {
                "risk_level": "Low",
                "description": "Irregular Website/IP Usage",
                "destination_ip": "2001:4860:4802:32::223",
                "process_name": "Unknown",
                "metrics": "CPU: 18.3% | Mem: 87.3% | Net Tx: 0.0016MB/s",
                "root_cause": "Endpoint navigated to an IP that is not in its historical baseline.",
                "remediation": "1. Log IP 2001:4860:4802:32::223 for threat intel correlation. 2. No immediate action required.",
                "frequency": 17,
                "source_ip": "127.0.0.1"
            }
        },
        "previous_hash": "137b2e9c97f2a0da58c28009bdb85287a3884efd8ed77d847f2c54bc03356030",
        "hash": "6cbceed556d85d87f92b6d6a5c5e2e0e03fb9d8c99b4483671553d3fd3158c56"
    },
    {
        "index": 21,
        "timestamp": 1777702080.1522417,
        "data": {
            "type": "ALERT",
            "alert_id": "9e289a54-cc44-45aa-8db0-fe631974e94a",
            "endpoint_id": "SachinChauhan",
            "timestamp": 1777702069.9240668,
            "risk_level": "Low",
            "details": {
                "risk_level": "Low",
                "description": "Irregular Website/IP Usage",
                "destination_ip": "2600:1417:56:289::3114",
                "process_name": "Unknown",
                "metrics": "CPU: 18.3% | Mem: 87.3% | Net Tx: 0.0016MB/s",
                "root_cause": "Endpoint navigated to an IP that is not in its historical baseline.",
                "remediation": "1. Log IP 2600:1417:56:289::3114 for threat intel correlation. 2. No immediate action required.",
                "frequency": 18,
                "source_ip": "127.0.0.1"
            }
        },
        "previous_hash": "6cbceed556d85d87f92b6d6a5c5e2e0e03fb9d8c99b4483671553d3fd3158c56",
        "hash": "38ecdbc5471969ee490ff74822464c9451b107a1cb67416e72cae826ea5e5b25"
    },
    {
        "index": 22,
        "timestamp": 1777702082.1818259,
        "data": {
            "type": "ALERT",
            "alert_id": "d695a3eb-01ac-40c2-88d1-4ff6870c8035",
            "endpoint_id": "SachinChauhan",
            "timestamp": 1777702069.9240668,
            "risk_level": "Low",
            "details": {
                "risk_level": "Low",
                "description": "Irregular Website/IP Usage",
                "destination_ip": "2404:6800:4002:809::2001",
                "process_name": "Unknown",
                "metrics": "CPU: 18.3% | Mem: 87.3% | Net Tx: 0.0016MB/s",
                "root_cause": "Endpoint navigated to an IP that is not in its historical baseline.",
                "remediation": "1. Log IP 2404:6800:4002:809::2001 for threat intel correlation. 2. No immediate action required.",
                "frequency": 19,
                "source_ip": "127.0.0.1"
            }
        },
        "previous_hash": "38ecdbc5471969ee490ff74822464c9451b107a1cb67416e72cae826ea5e5b25",
        "hash": "51108b24b6989d5874b577b6d9fe544de81888750ac5e2a73b4f794e7fd180b9"
    },
    {
        "index": 23,
        "timestamp": 1777702089.1660874,
        "data": {
            "type": "ALERT",
            "alert_id": "4357b65a-b281-4fd2-b1db-a73e8e030e77",
            "endpoint_id": "SachinChauhan",
            "timestamp": 1777702084.9919496,
            "risk_level": "Low",
            "details": {
                "risk_level": "Low",
                "description": "Irregular Website/IP Usage",
                "destination_ip": "2600:1417:56:185::57",
                "process_name": "Unknown",
                "metrics": "CPU: 36.4% | Mem: 87.0% | Net Tx: 0.0008MB/s",
                "root_cause": "Endpoint navigated to an IP that is not in its historical baseline.",
                "remediation": "1. Log IP 2600:1417:56:185::57 for threat intel correlation. 2. No immediate action required.",
                "frequency": 20,
                "source_ip": "127.0.0.1"
            }
        },
        "previous_hash": "51108b24b6989d5874b577b6d9fe544de81888750ac5e2a73b4f794e7fd180b9",
        "hash": "c0665ebe42d9fd443f956fb2bf312d836adc82417c4f725ab074b9b821b9efa2"
    },
    {
        "index": 24,
        "timestamp": 1777702091.1878133,
        "data": {
            "type": "ALERT",
            "alert_id": "cbefadc2-0eac-4842-94db-3a1a90d71004",
            "endpoint_id": "SachinChauhan",
            "timestamp": 1777702084.9919496,
            "risk_level": "Low",
            "details": {
                "risk_level": "Low",
                "description": "Irregular Website/IP Usage",
                "destination_ip": "40.126.18.32",
                "process_name": "Unknown",
                "metrics": "CPU: 36.4% | Mem: 87.0% | Net Tx: 0.0008MB/s",
                "root_cause": "Endpoint navigated to an IP that is not in its historical baseline.",
                "remediation": "1. Log IP 40.126.18.32 for threat intel correlation. 2. No immediate action required.",
                "frequency": 21,
                "source_ip": "127.0.0.1"
            }
        },
        "previous_hash": "c0665ebe42d9fd443f956fb2bf312d836adc82417c4f725ab074b9b821b9efa2",
        "hash": "abcd4481bf03179177520e6b577dcfca518e43b771bc36ce8b8b7e5e628d013f"
    },
    {
        "index": 25,
        "timestamp": 1777702093.2154458,
        "data": {
            "type": "ALERT",
            "alert_id": "804ba789-a461-4d07-b74e-d41f1572772e",
            "endpoint_id": "SachinChauhan",
            "timestamp": 1777702084.9919496,
            "risk_level": "Low",
            "details": {
                "risk_level": "Low",
                "description": "Irregular Website/IP Usage",
                "destination_ip": "2001:4860:4802:32::223",
                "process_name": "Unknown",
                "metrics": "CPU: 36.4% | Mem: 87.0% | Net Tx: 0.0008MB/s",
                "root_cause": "Endpoint navigated to an IP that is not in its historical baseline.",
                "remediation": "1. Log IP 2001:4860:4802:32::223 for threat intel correlation. 2. No immediate action required.",
                "frequency": 22,
                "source_ip": "127.0.0.1"
            }
        },
        "previous_hash": "abcd4481bf03179177520e6b577dcfca518e43b771bc36ce8b8b7e5e628d013f",
        "hash": "ba77541ff1d4f33249a012fcdde855af4aaf2fd071753807036681805fb3ce78"
    },
    {
        "index": 26,
        "timestamp": 1777702095.2373242,
        "data": {
            "type": "ALERT",
            "alert_id": "bc83ada5-8874-4ca2-aba1-e5e2822bb3b1",
            "endpoint_id": "SachinChauhan",
            "timestamp": 1777702084.9919496,
            "risk_level": "Low",
            "details": {
                "risk_level": "Low",
                "description": "Irregular Website/IP Usage",
                "destination_ip": "2600:1417:56:289::3114",
                "process_name": "Unknown",
                "metrics": "CPU: 36.4% | Mem: 87.0% | Net Tx: 0.0008MB/s",
                "root_cause": "Endpoint navigated to an IP that is not in its historical baseline.",
                "remediation": "1. Log IP 2600:1417:56:289::3114 for threat intel correlation. 2. No immediate action required.",
                "frequency": 23,
                "source_ip": "127.0.0.1"
            }
        },
        "previous_hash": "ba77541ff1d4f33249a012fcdde855af4aaf2fd071753807036681805fb3ce78",
        "hash": "bcdc6c62f09ef930a96ce204a217f91353508bab8669b20b8520c5eec6f59fa2"
    },
    {
        "index": 27,
        "timestamp": 1777702097.265342,
        "data": {
            "type": "ALERT",
            "alert_id": "fbdf9ca2-a433-4f3f-8209-38ae875ae772",
            "endpoint_id": "SachinChauhan",
            "timestamp": 1777702084.9919496,
            "risk_level": "Low",
            "details": {
                "risk_level": "Low",
                "description": "Irregular Website/IP Usage",
                "destination_ip": "2404:6800:4002:809::2001",
                "process_name": "Unknown",
                "metrics": "CPU: 36.4% | Mem: 87.0% | Net Tx: 0.0008MB/s",
                "root_cause": "Endpoint navigated to an IP that is not in its historical baseline.",
                "remediation": "1. Log IP 2404:6800:4002:809::2001 for threat intel correlation. 2. No immediate action required.",
                "frequency": 24,
                "source_ip": "127.0.0.1"
            }
        },
        "previous_hash": "bcdc6c62f09ef930a96ce204a217f91353508bab8669b20b8520c5eec6f59fa2",
        "hash": "b6635bf4e70cfbbf4c758900357a0fd0d7a6b7848d5b018f456ac967859a9b56"
    },
    {
        "index": 28,
        "timestamp": 1777702109.2749152,
        "data": {
            "type": "ALERT",
            "alert_id": "57abb2d8-0434-4fbf-a03e-c3244593ef8e",
            "endpoint_id": "SachinChauhan",
            "timestamp": 1777702105.0836756,
            "risk_level": "Low",
            "details": {
                "risk_level": "Low",
                "description": "Irregular Website/IP Usage",
                "destination_ip": "2600:1417:56:185::57",
                "process_name": "Unknown",
                "metrics": "CPU: 32.3% | Mem: 86.3% | Net Tx: 0.0003MB/s",
                "root_cause": "Endpoint navigated to an IP that is not in its historical baseline.",
                "remediation": "1. Log IP 2600:1417:56:185::57 for threat intel correlation. 2. No immediate action required.",
                "frequency": 25,
                "source_ip": "127.0.0.1"
            }
        },
        "previous_hash": "b6635bf4e70cfbbf4c758900357a0fd0d7a6b7848d5b018f456ac967859a9b56",
        "hash": "ed6af4284a9249dc6c70a0ed40daa4db380d2507fe361ec16affc62688620665"
    },
    {
        "index": 29,
        "timestamp": 1777702111.3008754,
        "data": {
            "type": "ALERT",
            "alert_id": "e38b3f00-0b6e-4db0-9334-78a6e709f102",
            "endpoint_id": "SachinChauhan",
            "timestamp": 1777702105.0836756,
            "risk_level": "Low",
            "details": {
                "risk_level": "Low",
                "description": "Irregular Website/IP Usage",
                "destination_ip": "40.126.18.32",
                "process_name": "Unknown",
                "metrics": "CPU: 32.3% | Mem: 86.3% | Net Tx: 0.0003MB/s",
                "root_cause": "Endpoint navigated to an IP that is not in its historical baseline.",
                "remediation": "1. Log IP 40.126.18.32 for threat intel correlation. 2. No immediate action required.",
                "frequency": 26,
                "source_ip": "127.0.0.1"
            }
        },
        "previous_hash": "ed6af4284a9249dc6c70a0ed40daa4db380d2507fe361ec16affc62688620665",
        "hash": "c12ccb23dbf97d2f2152667b2b108023b04dada383a326268b96e6ed3a4d0281"
    },
    {
        "index": 30,
        "timestamp": 1777702113.3249316,
        "data": {
            "type": "ALERT",
            "alert_id": "a7993048-42bf-41c9-87c2-c456ffdc21da",
            "endpoint_id": "SachinChauhan",
            "timestamp": 1777702105.0836756,
            "risk_level": "Low",
            "details": {
                "risk_level": "Low",
                "description": "Irregular Website/IP Usage",
                "destination_ip": "2001:4860:4802:32::223",
                "process_name": "Unknown",
                "metrics": "CPU: 32.3% | Mem: 86.3% | Net Tx: 0.0003MB/s",
                "root_cause": "Endpoint navigated to an IP that is not in its historical baseline.",
                "remediation": "1. Log IP 2001:4860:4802:32::223 for threat intel correlation. 2. No immediate action required.",
                "frequency": 27,
                "source_ip": "127.0.0.1"
            }
        },
        "previous_hash": "c12ccb23dbf97d2f2152667b2b108023b04dada383a326268b96e6ed3a4d0281",
        "hash": "f570fbaca50c1be6fd2cd74429de2771a34e37176f604a36b2d630f9486bcd65"
    },
    {
        "index": 31,
        "timestamp": 1777702115.349373,
        "data": {
            "type": "ALERT",
            "alert_id": "68b41da8-dd55-4cf5-add7-73ddba68479e",
            "endpoint_id": "SachinChauhan",
            "timestamp": 1777702105.0836756,
            "risk_level": "Low",
            "details": {
                "risk_level": "Low",
                "description": "Irregular Website/IP Usage",
                "destination_ip": "2600:1417:56:289::3114",
                "process_name": "Unknown",
                "metrics": "CPU: 32.3% | Mem: 86.3% | Net Tx: 0.0003MB/s",
                "root_cause": "Endpoint navigated to an IP that is not in its historical baseline.",
                "remediation": "1. Log IP 2600:1417:56:289::3114 for threat intel correlation. 2. No immediate action required.",
                "frequency": 28,
                "source_ip": "127.0.0.1"
            }
        },
        "previous_hash": "f570fbaca50c1be6fd2cd74429de2771a34e37176f604a36b2d630f9486bcd65",
        "hash": "2743f91baa415da2b2cb11d9fe43cc2961d5f378ee5c9b422e10e635134f8727"
    },
    {
        "index": 32,
        "timestamp": 1777702117.3778508,
        "data": {
            "type": "ALERT",
            "alert_id": "c599f4b0-56bc-4f50-9b35-ac0b73532f94",
            "endpoint_id": "SachinChauhan",
            "timestamp": 1777702105.0836756,
            "risk_level": "Low",
            "details": {
                "risk_level": "Low",
                "description": "Irregular Website/IP Usage",
                "destination_ip": "2404:6800:4002:809::2001",
                "process_name": "Unknown",
                "metrics": "CPU: 32.3% | Mem: 86.3% | Net Tx: 0.0003MB/s",
                "root_cause": "Endpoint navigated to an IP that is not in its historical baseline.",
                "remediation": "1. Log IP 2404:6800:4002:809::2001 for threat intel correlation. 2. No immediate action required.",
                "frequency": 29,
                "source_ip": "127.0.0.1"
            }
        },
        "previous_hash": "2743f91baa415da2b2cb11d9fe43cc2961d5f378ee5c9b422e10e635134f8727",
        "hash": "7de5e9e8f6b2905ec1b355e38da39cbeb5b67f414525343f35b007ea0569ac75"
    },
    {
        "index": 33,
        "timestamp": 1777702139.3683548,
        "data": {
            "type": "ALERT",
            "alert_id": "90ecaf60-58b4-4793-a18b-e200db2ebe63",
            "endpoint_id": "SachinChauhan",
            "timestamp": 1777702135.1979828,
            "risk_level": "Medium",
            "details": {
                "risk_level": "Medium",
                "description": "Unknown Process Executed: sppsvc.exe",
                "destination_ip": "N/A",
                "process_name": "sppsvc.exe",
                "metrics": "CPU: 34.4% | Mem: 86.5% | Net Tx: 0.0003MB/s",
                "root_cause": "A benign-looking application was started that has never been used by this user.",
                "remediation": "1. Verify if 'sppsvc.exe' is company-approved. 2. Monitor for further anomalous actions.",
                "frequency": 1,
                "source_ip": "127.0.0.1"
            }
        },
        "previous_hash": "7de5e9e8f6b2905ec1b355e38da39cbeb5b67f414525343f35b007ea0569ac75",
        "hash": "aa85b6bab6d666459623846ebe7bd337b44c3d7448eed4f1c77c701f6e79e9c2"
    },
    {
        "index": 34,
        "timestamp": 1777702141.3964522,
        "data": {
            "type": "ALERT",
            "alert_id": "9dd6fb63-e437-49df-b83d-26ce16c4df39",
            "endpoint_id": "SachinChauhan",
            "timestamp": 1777702135.1979828,
            "risk_level": "Low",
            "details": {
                "risk_level": "Low",
                "description": "Irregular Website/IP Usage",
                "destination_ip": "2600:1417:56:185::57",
                "process_name": "Unknown",
                "metrics": "CPU: 34.4% | Mem: 86.5% | Net Tx: 0.0003MB/s",
                "root_cause": "Endpoint navigated to an IP that is not in its historical baseline.",
                "remediation": "1. Log IP 2600:1417:56:185::57 for threat intel correlation. 2. No immediate action required.",
                "frequency": 30,
                "source_ip": "127.0.0.1"
            }
        },
        "previous_hash": "aa85b6bab6d666459623846ebe7bd337b44c3d7448eed4f1c77c701f6e79e9c2",
        "hash": "23520a4c1868c405c3281832b98ec5dccd5ebc75adba9e821986fef28897efbf"
    },
    {
        "index": 35,
        "timestamp": 1777702143.4151535,
        "data": {
            "type": "ALERT",
            "alert_id": "1a31b99c-9ccf-4157-aef2-399ce37e3c10",
            "endpoint_id": "SachinChauhan",
            "timestamp": 1777702135.1979828,
            "risk_level": "Low",
            "details": {
                "risk_level": "Low",
                "description": "Irregular Website/IP Usage",
                "destination_ip": "2001:4860:4802:32::223",
                "process_name": "Unknown",
                "metrics": "CPU: 34.4% | Mem: 86.5% | Net Tx: 0.0003MB/s",
                "root_cause": "Endpoint navigated to an IP that is not in its historical baseline.",
                "remediation": "1. Log IP 2001:4860:4802:32::223 for threat intel correlation. 2. No immediate action required.",
                "frequency": 31,
                "source_ip": "127.0.0.1"
            }
        },
        "previous_hash": "23520a4c1868c405c3281832b98ec5dccd5ebc75adba9e821986fef28897efbf",
        "hash": "42cf7c588f749228686ec91643ce34b98f30cbba4fa549c367dc2d683dce4c40"
    },
    {
        "index": 36,
        "timestamp": 1777702145.4671896,
        "data": {
            "type": "ALERT",
            "alert_id": "e58c08e1-b28e-48fb-928a-377934b1672d",
            "endpoint_id": "SachinChauhan",
            "timestamp": 1777702135.1979828,
            "risk_level": "Low",
            "details": {
                "risk_level": "Low",
                "description": "Irregular Website/IP Usage",
                "destination_ip": "52.185.211.133",
                "process_name": "Unknown",
                "metrics": "CPU: 34.4% | Mem: 86.5% | Net Tx: 0.0003MB/s",
                "root_cause": "Endpoint navigated to an IP that is not in its historical baseline.",
                "remediation": "1. Log IP 52.185.211.133 for threat intel correlation. 2. No immediate action required.",
                "frequency": 32,
                "source_ip": "127.0.0.1"
            }
        },
        "previous_hash": "42cf7c588f749228686ec91643ce34b98f30cbba4fa549c367dc2d683dce4c40",
        "hash": "8f3d113dd4aff5e5bae249d1da1db585f31dfd31c7ef52a691b738081156908a"
    },
    {
        "index": 37,
        "timestamp": 1777702147.491104,
        "data": {
            "type": "ALERT",
            "alert_id": "ca65ad87-9ae6-4d29-9327-d958d16930f7",
            "endpoint_id": "SachinChauhan",
            "timestamp": 1777702135.1979828,
            "risk_level": "Low",
            "details": {
                "risk_level": "Low",
                "description": "Irregular Website/IP Usage",
                "destination_ip": "2404:6800:4002:809::2001",
                "process_name": "Unknown",
                "metrics": "CPU: 34.4% | Mem: 86.5% | Net Tx: 0.0003MB/s",
                "root_cause": "Endpoint navigated to an IP that is not in its historical baseline.",
                "remediation": "1. Log IP 2404:6800:4002:809::2001 for threat intel correlation. 2. No immediate action required.",
                "frequency": 33,
                "source_ip": "127.0.0.1"
            }
        },
        "previous_hash": "8f3d113dd4aff5e5bae249d1da1db585f31dfd31c7ef52a691b738081156908a",
        "hash": "e738f62982bf65336fef53cdfcdc24fe5add78d585383674d42b414c3aa9f9db"
    },
    {
        "index": 38,
        "timestamp": 1777702246.7198033,
        "data": {
            "type": "ALERT",
            "alert_id": "93697186-326b-4a9d-9305-3fed13cc3223",
            "endpoint_id": "SachinChauhan",
            "timestamp": 1777702242.583063,
            "risk_level": "Low",
            "details": {
                "risk_level": "Low",
                "description": "Irregular Website/IP Usage",
                "destination_ip": "13.107.5.93",
                "process_name": "Unknown",
                "metrics": "CPU: 30.6% | Mem: 85.3% | Net Tx: 0.0005MB/s",
                "root_cause": "Endpoint navigated to an IP that is not in its historical baseline.",
                "remediation": "1. Log IP 13.107.5.93 for threat intel correlation. 2. No immediate action required.",
                "frequency": 34,
                "source_ip": "127.0.0.1"
            }
        },
        "previous_hash": "e738f62982bf65336fef53cdfcdc24fe5add78d585383674d42b414c3aa9f9db",
        "hash": "06e66644cedfdd8d29b2154a72c2f179bb8f09e9ff2cb409095a85c246c0aa20"
    },
    {
        "index": 39,
        "timestamp": 1777702270.2204547,
        "data": {
            "type": "ALERT",
            "alert_id": "9af94213-40ea-45c6-822b-4c7b5a8223d8",
            "endpoint_id": "SachinChauhan",
            "timestamp": 1777702266.0619562,
            "risk_level": "Low",
            "details": {
                "risk_level": "Low",
                "description": "Minor Behavioral Deviation",
                "destination_ip": "N/A",
                "process_name": "N/A",
                "metrics": "CPU: 33.7% | Mem: 84.6% | Net Tx: 0.0037MB/s",
                "root_cause": "General resource consumption pattern shifted slightly from the ML baseline.",
                "remediation": "1. No immediate action required. 2. Log for future behavioral auditing.",
                "frequency": 1,
                "source_ip": "127.0.0.1"
            }
        },
        "previous_hash": "06e66644cedfdd8d29b2154a72c2f179bb8f09e9ff2cb409095a85c246c0aa20",
        "hash": "01a59465d8bd49d73eed0b711e3e708abe19a696d147d569223d4d2f8a51d59d"
    },
    {
        "index": 40,
        "timestamp": 1777702272.27002,
        "data": {
            "type": "ALERT",
            "alert_id": "9059d553-4bef-488f-bd6c-44a8d8fb0ccc",
            "endpoint_id": "SachinChauhan",
            "timestamp": 1777702266.0619562,
            "risk_level": "Low",
            "details": {
                "risk_level": "Low",
                "description": "Irregular Website/IP Usage",
                "destination_ip": "2607:f8b0:4004:1001::5e",
                "process_name": "Unknown",
                "metrics": "CPU: 33.7% | Mem: 84.6% | Net Tx: 0.0037MB/s",
                "root_cause": "Endpoint navigated to an IP that is not in its historical baseline.",
                "remediation": "1. Log IP 2607:f8b0:4004:1001::5e for threat intel correlation. 2. No immediate action required.",
                "frequency": 35,
                "source_ip": "127.0.0.1"
            }
        },
        "previous_hash": "01a59465d8bd49d73eed0b711e3e708abe19a696d147d569223d4d2f8a51d59d",
        "hash": "901e2108dd1b9d49e883d86b602dc685773ba0d930ad7581df8d5e6290cc28b5"
    },
    {
        "index": 41,
        "timestamp": 1777702274.319981,
        "data": {
            "type": "ALERT",
            "alert_id": "a84eb1ad-1940-4cdd-af9b-d40533b32a8a",
            "endpoint_id": "SachinChauhan",
            "timestamp": 1777702266.0619562,
            "risk_level": "Low",
            "details": {
                "risk_level": "Low",
                "description": "Irregular Website/IP Usage",
                "destination_ip": "35.186.134.240",
                "process_name": "Unknown",
                "metrics": "CPU: 33.7% | Mem: 84.6% | Net Tx: 0.0037MB/s",
                "root_cause": "Endpoint navigated to an IP that is not in its historical baseline.",
                "remediation": "1. Log IP 35.186.134.240 for threat intel correlation. 2. No immediate action required.",
                "frequency": 36,
                "source_ip": "127.0.0.1"
            }
        },
        "previous_hash": "901e2108dd1b9d49e883d86b602dc685773ba0d930ad7581df8d5e6290cc28b5",
        "hash": "cce996d3155eca95914944c9f32ace19f7435ec1b7597f2a195f8a12afec5467"
    },
    {
        "index": 42,
        "timestamp": 1777702283.5532792,
        "data": {
            "type": "ALERT",
            "alert_id": "ef4ad0fc-6293-4331-b5a6-d3496e09a8df",
            "endpoint_id": "SachinChauhan",
            "timestamp": 1777702279.3842323,
            "risk_level": "Low",
            "details": {
                "risk_level": "Low",
                "description": "Irregular Website/IP Usage",
                "destination_ip": "2607:f8b0:4004:1001::5e",
                "process_name": "Unknown",
                "metrics": "CPU: 32.8% | Mem: 84.7% | Net Tx: 0.0003MB/s",
                "root_cause": "Endpoint navigated to an IP that is not in its historical baseline.",
                "remediation": "1. Log IP 2607:f8b0:4004:1001::5e for threat intel correlation. 2. No immediate action required.",
                "frequency": 37,
                "source_ip": "127.0.0.1"
            }
        },
        "previous_hash": "cce996d3155eca95914944c9f32ace19f7435ec1b7597f2a195f8a12afec5467",
        "hash": "f9c1efbaa07f7cde657e5ce9c1151fa3bc0edf2c7de66b358b876667b94e5384"
    },
    {
        "index": 43,
        "timestamp": 1777702285.5757651,
        "data": {
            "type": "ALERT",
            "alert_id": "4810a778-651c-4b3f-a481-907e6b86962d",
            "endpoint_id": "SachinChauhan",
            "timestamp": 1777702279.3842323,
            "risk_level": "Low",
            "details": {
                "risk_level": "Low",
                "description": "Irregular Website/IP Usage",
                "destination_ip": "35.186.134.240",
                "process_name": "Unknown",
                "metrics": "CPU: 32.8% | Mem: 84.7% | Net Tx: 0.0003MB/s",
                "root_cause": "Endpoint navigated to an IP that is not in its historical baseline.",
                "remediation": "1. Log IP 35.186.134.240 for threat intel correlation. 2. No immediate action required.",
                "frequency": 38,
                "source_ip": "127.0.0.1"
            }
        },
        "previous_hash": "f9c1efbaa07f7cde657e5ce9c1151fa3bc0edf2c7de66b358b876667b94e5384",
        "hash": "97d6f0a031b7e6793e2f1cb2a1e4ea33f32497fc320cb71c182e52baf0983ed6"
    },
    {
        "index": 44,
        "timestamp": 1777702294.7745717,
        "data": {
            "type": "ALERT",
            "alert_id": "d64dda71-f536-48ac-ab3a-3557196344de",
            "endpoint_id": "SachinChauhan",
            "timestamp": 1777702290.643904,
            "risk_level": "Low",
            "details": {
                "risk_level": "Low",
                "description": "Irregular Website/IP Usage",
                "destination_ip": "2607:f8b0:4004:1001::5e",
                "process_name": "Unknown",
                "metrics": "CPU: 30.0% | Mem: 84.3% | Net Tx: 0.0006MB/s",
                "root_cause": "Endpoint navigated to an IP that is not in its historical baseline.",
                "remediation": "1. Log IP 2607:f8b0:4004:1001::5e for threat intel correlation. 2. No immediate action required.",
                "frequency": 39,
                "source_ip": "127.0.0.1"
            }
        },
        "previous_hash": "97d6f0a031b7e6793e2f1cb2a1e4ea33f32497fc320cb71c182e52baf0983ed6",
        "hash": "6a3904dd6a3e2bc5204f68791f42682c1d133af7af0a0ed1fb89d79e63aa8738"
    },
    {
        "index": 45,
        "timestamp": 1777702296.8087919,
        "data": {
            "type": "ALERT",
            "alert_id": "0296b036-8ebc-4eef-869e-a5eda74b63a2",
            "endpoint_id": "SachinChauhan",
            "timestamp": 1777702290.643904,
            "risk_level": "Low",
            "details": {
                "risk_level": "Low",
                "description": "Irregular Website/IP Usage",
                "destination_ip": "35.186.134.240",
                "process_name": "Unknown",
                "metrics": "CPU: 30.0% | Mem: 84.3% | Net Tx: 0.0006MB/s",
                "root_cause": "Endpoint navigated to an IP that is not in its historical baseline.",
                "remediation": "1. Log IP 35.186.134.240 for threat intel correlation. 2. No immediate action required.",
                "frequency": 40,
                "source_ip": "127.0.0.1"
            }
        },
        "previous_hash": "6a3904dd6a3e2bc5204f68791f42682c1d133af7af0a0ed1fb89d79e63aa8738",
        "hash": "7667ff167259fd6bf2f5e5bb7ad8348bc0e908873c9ffae09771b6f67d4c91d5"
    },
    {
        "index": 46,
        "timestamp": 1777702306.033071,
        "data": {
            "type": "ALERT",
            "alert_id": "411d9e9b-0020-4810-9854-5d2317f31b96",
            "endpoint_id": "SachinChauhan",
            "timestamp": 1777702301.886395,
            "risk_level": "Low",
            "details": {
                "risk_level": "Low",
                "description": "Irregular Website/IP Usage",
                "destination_ip": "2607:f8b0:4004:1001::5e",
                "process_name": "Unknown",
                "metrics": "CPU: 34.0% | Mem: 84.7% | Net Tx: 0.0001MB/s",
                "root_cause": "Endpoint navigated to an IP that is not in its historical baseline.",
                "remediation": "1. Log IP 2607:f8b0:4004:1001::5e for threat intel correlation. 2. No immediate action required.",
                "frequency": 41,
                "source_ip": "127.0.0.1"
            }
        },
        "previous_hash": "7667ff167259fd6bf2f5e5bb7ad8348bc0e908873c9ffae09771b6f67d4c91d5",
        "hash": "4989efae8a74ccf7602bfd55a2c21af309b252caae1e3a3f8f970efed859b137"
    },
    {
        "index": 47,
        "timestamp": 1777702315.21825,
        "data": {
            "type": "ALERT",
            "alert_id": "2399b6c7-0e03-46bd-a0a8-ce920ce9d4e1",
            "endpoint_id": "SachinChauhan",
            "timestamp": 1777702311.0868375,
            "risk_level": "Low",
            "details": {
                "risk_level": "Low",
                "description": "Irregular Website/IP Usage",
                "destination_ip": "2607:f8b0:4004:1001::5e",
                "process_name": "Unknown",
                "metrics": "CPU: 34.1% | Mem: 84.6% | Net Tx: 0.0002MB/s",
                "root_cause": "Endpoint navigated to an IP that is not in its historical baseline.",
                "remediation": "1. Log IP 2607:f8b0:4004:1001::5e for threat intel correlation. 2. No immediate action required.",
                "frequency": 42,
                "source_ip": "127.0.0.1"
            }
        },
        "previous_hash": "4989efae8a74ccf7602bfd55a2c21af309b252caae1e3a3f8f970efed859b137",
        "hash": "5d0927eb8ee29c5e16c40f9116bd2db8a6458f286a1ee4ad3e0f5d9dc24ec09b"
    },
    {
        "index": 48,
        "timestamp": 1777702324.4370744,
        "data": {
            "type": "ALERT",
            "alert_id": "e8d0b2bd-7d71-4f08-87c7-25fdd0607817",
            "endpoint_id": "SachinChauhan",
            "timestamp": 1777702320.2842052,
            "risk_level": "Low",
            "details": {
                "risk_level": "Low",
                "description": "Irregular Website/IP Usage",
                "destination_ip": "2607:f8b0:4004:1001::5e",
                "process_name": "Unknown",
                "metrics": "CPU: 32.3% | Mem: 84.6% | Net Tx: 0.0002MB/s",
                "root_cause": "Endpoint navigated to an IP that is not in its historical baseline.",
                "remediation": "1. Log IP 2607:f8b0:4004:1001::5e for threat intel correlation. 2. No immediate action required.",
                "frequency": 43,
                "source_ip": "127.0.0.1"
            }
        },
        "previous_hash": "5d0927eb8ee29c5e16c40f9116bd2db8a6458f286a1ee4ad3e0f5d9dc24ec09b",
        "hash": "a5daeb1a718ec216a53a21172d2c5536708dba09a4806f496ad0a9413b5c7ce7"
    },
    {
        "index": 49,
        "timestamp": 1777702347.888302,
        "data": {
            "type": "ALERT",
            "alert_id": "829645c6-5f27-4473-902b-4f07ec94ff78",
            "endpoint_id": "SachinChauhan",
            "timestamp": 1777702343.7587078,
            "risk_level": "Low",
            "details": {
                "risk_level": "Low",
                "description": "Minor Behavioral Deviation",
                "destination_ip": "N/A",
                "process_name": "N/A",
                "metrics": "CPU: 40.3% | Mem: 86.0% | Net Tx: 0.0013MB/s",
                "root_cause": "General resource consumption pattern shifted slightly from the ML baseline.",
                "remediation": "1. No immediate action required. 2. Log for future behavioral auditing.",
                "frequency": 2,
                "source_ip": "127.0.0.1"
            }
        },
        "previous_hash": "a5daeb1a718ec216a53a21172d2c5536708dba09a4806f496ad0a9413b5c7ce7",
        "hash": "7d281783b558f0b55a7191b034108ea6377f678417f2503328790122e47f9dd1"
    },
    {
        "index": 50,
        "timestamp": 1777702371.4049008,
        "data": {
            "type": "ALERT",
            "alert_id": "1c602bef-7a8e-4bba-bb01-11da99fcece3",
            "endpoint_id": "SachinChauhan",
            "timestamp": 1777702367.2726066,
            "risk_level": "Medium",
            "details": {
                "risk_level": "Medium",
                "description": "Unknown Process Executed: hxtsr.exe",
                "destination_ip": "N/A",
                "process_name": "hxtsr.exe",
                "metrics": "CPU: 41.5% | Mem: 87.5% | Net Tx: 0.0021MB/s",
                "root_cause": "A benign-looking application was started that has never been used by this user.",
                "remediation": "1. Verify if 'hxtsr.exe' is company-approved. 2. Monitor for further anomalous actions.",
                "frequency": 1,
                "source_ip": "127.0.0.1"
            }
        },
        "previous_hash": "7d281783b558f0b55a7191b034108ea6377f678417f2503328790122e47f9dd1",
        "hash": "3d137b52c77099ef342734b7456145b0d5927ca9ad680e5e94e6681f6a0f26b0"
    },
    {
        "index": 51,
        "timestamp": 1777702373.4383678,
        "data": {
            "type": "ALERT",
            "alert_id": "c37cc54d-1f5f-4291-b855-adcdab61910a",
            "endpoint_id": "SachinChauhan",
            "timestamp": 1777702367.2726066,
            "risk_level": "Medium",
            "details": {
                "risk_level": "Medium",
                "description": "Unknown Process Executed: updater.exe",
                "destination_ip": "N/A",
                "process_name": "updater.exe",
                "metrics": "CPU: 41.5% | Mem: 87.5% | Net Tx: 0.0021MB/s",
                "root_cause": "A benign-looking application was started that has never been used by this user.",
                "remediation": "1. Verify if 'updater.exe' is company-approved. 2. Monitor for further anomalous actions.",
                "frequency": 1,
                "source_ip": "127.0.0.1"
            }
        },
        "previous_hash": "3d137b52c77099ef342734b7456145b0d5927ca9ad680e5e94e6681f6a0f26b0",
        "hash": "2a98ecfbf6c6a023f1be8119f0eea5366dd53f46858b1ddf3435ec8448e7f77c"
    },
    {
        "index": 52,
        "timestamp": 1777702382.630706,
        "data": {
            "type": "ALERT",
            "alert_id": "8588865b-0203-48ff-bfe0-6f58e01d2e8b",
            "endpoint_id": "SachinChauhan",
            "timestamp": 1777702378.4918997,
            "risk_level": "Medium",
            "details": {
                "risk_level": "Medium",
                "description": "Unknown Process Executed: hxtsr.exe",
                "destination_ip": "N/A",
                "process_name": "hxtsr.exe",
                "metrics": "CPU: 34.3% | Mem: 87.5% | Net Tx: 0.0026MB/s",
                "root_cause": "A benign-looking application was started that has never been used by this user.",
                "remediation": "1. Verify if 'hxtsr.exe' is company-approved. 2. Monitor for further anomalous actions.",
                "frequency": 2,
                "source_ip": "127.0.0.1"
            }
        },
        "previous_hash": "2a98ecfbf6c6a023f1be8119f0eea5366dd53f46858b1ddf3435ec8448e7f77c",
        "hash": "d693e408107affc3ee8509367b65d97639bf735ef64eaf7dcb27b77950995c1b"
    },
    {
        "index": 53,
        "timestamp": 1777702384.6730773,
        "data": {
            "type": "ALERT",
            "alert_id": "cfec60dd-8830-4bfa-9019-ad494a930ca9",
            "endpoint_id": "SachinChauhan",
            "timestamp": 1777702378.4918997,
            "risk_level": "Medium",
            "details": {
                "risk_level": "Medium",
                "description": "Unknown Process Executed: updater.exe",
                "destination_ip": "N/A",
                "process_name": "updater.exe",
                "metrics": "CPU: 34.3% | Mem: 87.5% | Net Tx: 0.0026MB/s",
                "root_cause": "A benign-looking application was started that has never been used by this user.",
                "remediation": "1. Verify if 'updater.exe' is company-approved. 2. Monitor for further anomalous actions.",
                "frequency": 2,
                "source_ip": "127.0.0.1"
            }
        },
        "previous_hash": "d693e408107affc3ee8509367b65d97639bf735ef64eaf7dcb27b77950995c1b",
        "hash": "56ceff3156dfc88e941cb2bc41bd62806100365890cfd0dbb3047459b8e728b8"
    },
    {
        "index": 54,
        "timestamp": 1777702386.6961348,
        "data": {
            "type": "ALERT",
            "alert_id": "4cfe4edd-da3f-46c3-9585-8f7134a7b704",
            "endpoint_id": "SachinChauhan",
            "timestamp": 1777702378.4918997,
            "risk_level": "Low",
            "details": {
                "risk_level": "Low",
                "description": "Irregular Website/IP Usage",
                "destination_ip": "2404:6800:4002:82a::2001",
                "process_name": "Unknown",
                "metrics": "CPU: 34.3% | Mem: 87.5% | Net Tx: 0.0026MB/s",
                "root_cause": "Endpoint navigated to an IP that is not in its historical baseline.",
                "remediation": "1. Log IP 2404:6800:4002:82a::2001 for threat intel correlation. 2. No immediate action required.",
                "frequency": 44,
                "source_ip": "127.0.0.1"
            }
        },
        "previous_hash": "56ceff3156dfc88e941cb2bc41bd62806100365890cfd0dbb3047459b8e728b8",
        "hash": "aafcba5768405c0eca9c49dd7c878f6d5dfcad741ef18d97829ac8b3fa82cc0d"
    },
    {
        "index": 55,
        "timestamp": 1777702395.929913,
        "data": {
            "type": "ALERT",
            "alert_id": "a5909df6-0e3a-4214-8125-dfa875224c7c",
            "endpoint_id": "SachinChauhan",
            "timestamp": 1777702391.7481387,
            "risk_level": "Medium",
            "details": {
                "risk_level": "Medium",
                "description": "Unknown Process Executed: hxtsr.exe",
                "destination_ip": "N/A",
                "process_name": "hxtsr.exe",
                "metrics": "CPU: 34.4% | Mem: 86.4% | Net Tx: 0.0008MB/s",
                "root_cause": "A benign-looking application was started that has never been used by this user.",
                "remediation": "1. Verify if 'hxtsr.exe' is company-approved. 2. Monitor for further anomalous actions.",
                "frequency": 3,
                "source_ip": "127.0.0.1"
            }
        },
        "previous_hash": "aafcba5768405c0eca9c49dd7c878f6d5dfcad741ef18d97829ac8b3fa82cc0d",
        "hash": "4c11f359dcd55caac29ae472e3d84de8fc593579315b4a13e72175b22c50ad47"
    },
    {
        "index": 56,
        "timestamp": 1777702397.9542253,
        "data": {
            "type": "ALERT",
            "alert_id": "43203709-37f1-4293-8dc0-6d32657de9bb",
            "endpoint_id": "SachinChauhan",
            "timestamp": 1777702391.7481387,
            "risk_level": "Low",
            "details": {
                "risk_level": "Low",
                "description": "Irregular Website/IP Usage",
                "destination_ip": "2404:6800:4002:82a::2001",
                "process_name": "Unknown",
                "metrics": "CPU: 34.4% | Mem: 86.4% | Net Tx: 0.0008MB/s",
                "root_cause": "Endpoint navigated to an IP that is not in its historical baseline.",
                "remediation": "1. Log IP 2404:6800:4002:82a::2001 for threat intel correlation. 2. No immediate action required.",
                "frequency": 45,
                "source_ip": "127.0.0.1"
            }
        },
        "previous_hash": "4c11f359dcd55caac29ae472e3d84de8fc593579315b4a13e72175b22c50ad47",
        "hash": "bd12c7beeac1574a648b995e621eefcf1e3d23b74b76ea98ac13eac1fd74c106"
    },
    {
        "index": 57,
        "timestamp": 1777702407.148242,
        "data": {
            "type": "ALERT",
            "alert_id": "604a6837-1261-4aea-9a1b-49b7cb8e0ca6",
            "endpoint_id": "SachinChauhan",
            "timestamp": 1777702402.9982164,
            "risk_level": "Low",
            "details": {
                "risk_level": "Low",
                "description": "Irregular Website/IP Usage",
                "destination_ip": "2404:6800:4002:82a::2001",
                "process_name": "Unknown",
                "metrics": "CPU: 32.8% | Mem: 86.4% | Net Tx: 0.0001MB/s",
                "root_cause": "Endpoint navigated to an IP that is not in its historical baseline.",
                "remediation": "1. Log IP 2404:6800:4002:82a::2001 for threat intel correlation. 2. No immediate action required.",
                "frequency": 46,
                "source_ip": "127.0.0.1"
            }
        },
        "previous_hash": "bd12c7beeac1574a648b995e621eefcf1e3d23b74b76ea98ac13eac1fd74c106",
        "hash": "6aeea43237e95edb74326509e06cc0e6af60ab9db96517f18398e4e2377ab2e5"
    },
    {
        "index": 58,
        "timestamp": 1777702416.4060895,
        "data": {
            "type": "ALERT",
            "alert_id": "5442c18f-e118-449e-8c4a-4956247b2283",
            "endpoint_id": "SachinChauhan",
            "timestamp": 1777702412.197899,
            "risk_level": "Low",
            "details": {
                "risk_level": "Low",
                "description": "Irregular Website/IP Usage",
                "destination_ip": "2404:6800:4002:82a::2001",
                "process_name": "Unknown",
                "metrics": "CPU: 39.8% | Mem: 86.4% | Net Tx: 0.0002MB/s",
                "root_cause": "Endpoint navigated to an IP that is not in its historical baseline.",
                "remediation": "1. Log IP 2404:6800:4002:82a::2001 for threat intel correlation. 2. No immediate action required.",
                "frequency": 47,
                "source_ip": "127.0.0.1"
            }
        },
        "previous_hash": "6aeea43237e95edb74326509e06cc0e6af60ab9db96517f18398e4e2377ab2e5",
        "hash": "7ce80228d7bdb5e9c7a36c8fc0dae15fa839977b7f8b70982a55b45f487c4fe0"
    },
    {
        "index": 59,
        "timestamp": 1777702425.6040463,
        "data": {
            "type": "ALERT",
            "alert_id": "4ad5236e-c4ec-44e8-9ef6-be498a223891",
            "endpoint_id": "SachinChauhan",
            "timestamp": 1777702421.448806,
            "risk_level": "Low",
            "details": {
                "risk_level": "Low",
                "description": "Irregular Website/IP Usage",
                "destination_ip": "2404:6800:4002:82a::2001",
                "process_name": "Unknown",
                "metrics": "CPU: 33.9% | Mem: 86.4% | Net Tx: 0.0008MB/s",
                "root_cause": "Endpoint navigated to an IP that is not in its historical baseline.",
                "remediation": "1. Log IP 2404:6800:4002:82a::2001 for threat intel correlation. 2. No immediate action required.",
                "frequency": 48,
                "source_ip": "127.0.0.1"
            }
        },
        "previous_hash": "7ce80228d7bdb5e9c7a36c8fc0dae15fa839977b7f8b70982a55b45f487c4fe0",
        "hash": "364a7a62c85df5fac11e9e2dc6b49ed14d3a3393bfead98ee6be4f85b77742eb"
    },
    {
        "index": 60,
        "timestamp": 1777702434.7968016,
        "data": {
            "type": "ALERT",
            "alert_id": "04ff80e9-0ec8-4200-a281-a011b96dfc7b",
            "endpoint_id": "SachinChauhan",
            "timestamp": 1777702430.6616077,
            "risk_level": "Low",
            "details": {
                "risk_level": "Low",
                "description": "Irregular Website/IP Usage",
                "destination_ip": "2404:6800:4002:82a::2001",
                "process_name": "Unknown",
                "metrics": "CPU: 32.0% | Mem: 86.6% | Net Tx: 0.0011MB/s",
                "root_cause": "Endpoint navigated to an IP that is not in its historical baseline.",
                "remediation": "1. Log IP 2404:6800:4002:82a::2001 for threat intel correlation. 2. No immediate action required.",
                "frequency": 49,
                "source_ip": "127.0.0.1"
            }
        },
        "previous_hash": "364a7a62c85df5fac11e9e2dc6b49ed14d3a3393bfead98ee6be4f85b77742eb",
        "hash": "8cb52a7ab2fd0570d5a494477a61fca5f1000b21fa2b78920a91d411435aa2a0"
    },
    {
        "index": 61,
        "timestamp": 1777702443.9973724,
        "data": {
            "type": "ALERT",
            "alert_id": "f1d90bd6-e498-4fa9-ae9e-62a7ef956e48",
            "endpoint_id": "SachinChauhan",
            "timestamp": 1777702439.8322906,
            "risk_level": "Low",
            "details": {
                "risk_level": "Low",
                "description": "Irregular Website/IP Usage",
                "destination_ip": "2404:6800:4002:82a::2001",
                "process_name": "Unknown",
                "metrics": "CPU: 35.5% | Mem: 86.4% | Net Tx: 0.0004MB/s",
                "root_cause": "Endpoint navigated to an IP that is not in its historical baseline.",
                "remediation": "1. Log IP 2404:6800:4002:82a::2001 for threat intel correlation. 2. No immediate action required.",
                "frequency": 50,
                "source_ip": "127.0.0.1"
            }
        },
        "previous_hash": "8cb52a7ab2fd0570d5a494477a61fca5f1000b21fa2b78920a91d411435aa2a0",
        "hash": "f1d679a52d4e9c6d2ca34850f2c63c50c34dff1d7f6e473ac72309c4538537df"
    },
    {
        "index": 62,
        "timestamp": 1777702453.2093189,
        "data": {
            "type": "ALERT",
            "alert_id": "fc8e963d-84ee-4856-abc2-1fff73aa49ba",
            "endpoint_id": "SachinChauhan",
            "timestamp": 1777702449.0555377,
            "risk_level": "Low",
            "details": {
                "risk_level": "Low",
                "description": "Irregular Website/IP Usage",
                "destination_ip": "2404:6800:4002:82a::2001",
                "process_name": "Unknown",
                "metrics": "CPU: 29.9% | Mem: 86.3% | Net Tx: 0.0009MB/s",
                "root_cause": "Endpoint navigated to an IP that is not in its historical baseline.",
                "remediation": "1. Log IP 2404:6800:4002:82a::2001 for threat intel correlation. 2. No immediate action required.",
                "frequency": 51,
                "source_ip": "127.0.0.1"
            }
        },
        "previous_hash": "f1d679a52d4e9c6d2ca34850f2c63c50c34dff1d7f6e473ac72309c4538537df",
        "hash": "3599a45369e3220b83b65db126a514a290fa4c07609c875700442a5684c1baf6"
    },
    {
        "index": 63,
        "timestamp": 1777702462.4129689,
        "data": {
            "type": "ALERT",
            "alert_id": "29d85440-2c5c-48d4-84b4-1e79c3bba9f6",
            "endpoint_id": "SachinChauhan",
            "timestamp": 1777702458.2564864,
            "risk_level": "Low",
            "details": {
                "risk_level": "Low",
                "description": "Irregular Website/IP Usage",
                "destination_ip": "2404:6800:4002:82a::2001",
                "process_name": "Unknown",
                "metrics": "CPU: 30.4% | Mem: 85.2% | Net Tx: 0.0002MB/s",
                "root_cause": "Endpoint navigated to an IP that is not in its historical baseline.",
                "remediation": "1. Log IP 2404:6800:4002:82a::2001 for threat intel correlation. 2. No immediate action required.",
                "frequency": 52,
                "source_ip": "127.0.0.1"
            }
        },
        "previous_hash": "3599a45369e3220b83b65db126a514a290fa4c07609c875700442a5684c1baf6",
        "hash": "0f5da30ca1c4dbabbe6cb0593b132029e9c7449558bc1323eacc28b28a705142"
    },
    {
        "index": 64,
        "timestamp": 1777702622.3129146,
        "data": {
            "type": "ALERT",
            "alert_id": "ef7e3bbe-8f4d-4fce-81b9-29e391660946",
            "endpoint_id": "SachinChauhan",
            "timestamp": 1777702618.164732,
            "risk_level": "Low",
            "details": {
                "risk_level": "Low",
                "description": "Minor Behavioral Deviation",
                "destination_ip": "N/A",
                "process_name": "N/A",
                "metrics": "CPU: 31.3% | Mem: 85.8% | Net Tx: 0.0039MB/s",
                "root_cause": "General resource consumption pattern shifted slightly from the ML baseline.",
                "remediation": "1. No immediate action required. 2. Log for future behavioral auditing.",
                "frequency": 3,
                "source_ip": "127.0.0.1"
            }
        },
        "previous_hash": "0f5da30ca1c4dbabbe6cb0593b132029e9c7449558bc1323eacc28b28a705142",
        "hash": "6ee6385a60fd616899f533424f9b1a9c6821ca03a022ef7bcab330fabc9979b2"
    },
    {
        "index": 65,
        "timestamp": 1777702638.7104907,
        "data": {
            "type": "ALERT",
            "alert_id": "44b80c9e-a491-44e1-a1cd-6d4deeb6e244",
            "endpoint_id": "SachinChauhan",
            "timestamp": 1777702634.5625682,
            "risk_level": "Low",
            "details": {
                "risk_level": "Low",
                "description": "Minor Behavioral Deviation",
                "destination_ip": "N/A",
                "process_name": "N/A",
                "metrics": "CPU: 31.9% | Mem: 85.8% | Net Tx: 0.0121MB/s",
                "root_cause": "General resource consumption pattern shifted slightly from the ML baseline.",
                "remediation": "1. No immediate action required. 2. Log for future behavioral auditing.",
                "frequency": 4,
                "source_ip": "127.0.0.1"
            }
        },
        "previous_hash": "6ee6385a60fd616899f533424f9b1a9c6821ca03a022ef7bcab330fabc9979b2",
        "hash": "538e191c2df62e5b2a8ad1e3720113a60f5ba8df33f4f40bb5e4d435a5e57692"
    },
    {
        "index": 66,
        "timestamp": 1777702647.9101841,
        "data": {
            "type": "ALERT",
            "alert_id": "1bf3f417-1227-4bd0-8bc1-abff4e885938",
            "endpoint_id": "SachinChauhan",
            "timestamp": 1777702643.769783,
            "risk_level": "Low",
            "details": {
                "risk_level": "Low",
                "description": "Minor Behavioral Deviation",
                "destination_ip": "N/A",
                "process_name": "N/A",
                "metrics": "CPU: 41.6% | Mem: 85.8% | Net Tx: 0.002MB/s",
                "root_cause": "General resource consumption pattern shifted slightly from the ML baseline.",
                "remediation": "1. No immediate action required. 2. Log for future behavioral auditing.",
                "frequency": 5,
                "source_ip": "127.0.0.1"
            }
        },
        "previous_hash": "538e191c2df62e5b2a8ad1e3720113a60f5ba8df33f4f40bb5e4d435a5e57692",
        "hash": "1ad6132be0993548d8ab1e3b74b81ec07f25278c0b8a91c1755e782b6efb7400"
    },
    {
        "index": 67,
        "timestamp": 1777702678.6109695,
        "data": {
            "type": "ALERT",
            "alert_id": "7ca6acb1-1cd5-4993-be42-e76bc835ddc4",
            "endpoint_id": "SachinChauhan",
            "timestamp": 1777702674.4671993,
            "risk_level": "Low",
            "details": {
                "risk_level": "Low",
                "description": "Minor Behavioral Deviation",
                "destination_ip": "N/A",
                "process_name": "N/A",
                "metrics": "CPU: 39.8% | Mem: 86.7% | Net Tx: 0.0042MB/s",
                "root_cause": "General resource consumption pattern shifted slightly from the ML baseline.",
                "remediation": "1. No immediate action required. 2. Log for future behavioral auditing.",
                "frequency": 6,
                "source_ip": "127.0.0.1"
            }
        },
        "previous_hash": "1ad6132be0993548d8ab1e3b74b81ec07f25278c0b8a91c1755e782b6efb7400",
        "hash": "ce15bb6c144ad458dc360f146a9b2975423cb941fadebb03bb60abd329502bba"
    },
    {
        "index": 68,
        "timestamp": 1777702695.0263677,
        "data": {
            "type": "ALERT",
            "alert_id": "b685ed82-4881-4faa-aa71-e07f588ea688",
            "endpoint_id": "SachinChauhan",
            "timestamp": 1777702690.8550029,
            "risk_level": "Low",
            "details": {
                "risk_level": "Low",
                "description": "Irregular Website/IP Usage",
                "destination_ip": "2620:1ec:bdf::68",
                "process_name": "Unknown",
                "metrics": "CPU: 28.5% | Mem: 86.7% | Net Tx: 0.0013MB/s",
                "root_cause": "Endpoint navigated to an IP that is not in its historical baseline.",
                "remediation": "1. Log IP 2620:1ec:bdf::68 for threat intel correlation. 2. No immediate action required.",
                "frequency": 53,
                "source_ip": "127.0.0.1"
            }
        },
        "previous_hash": "ce15bb6c144ad458dc360f146a9b2975423cb941fadebb03bb60abd329502bba",
        "hash": "7c15bffef9d9ee238350676c8d93196ed10d7615bff93906079fb7874c52625e"
    },
    {
        "index": 69,
        "timestamp": 1777702704.2669818,
        "data": {
            "type": "ALERT",
            "alert_id": "78bfe983-28b9-4949-ab06-8366f82534a3",
            "endpoint_id": "SachinChauhan",
            "timestamp": 1777702700.1074421,
            "risk_level": "Low",
            "details": {
                "risk_level": "Low",
                "description": "Irregular Website/IP Usage",
                "destination_ip": "2620:1ec:bdf::68",
                "process_name": "Unknown",
                "metrics": "CPU: 40.0% | Mem: 86.8% | Net Tx: 0.0001MB/s",
                "root_cause": "Endpoint navigated to an IP that is not in its historical baseline.",
                "remediation": "1. Log IP 2620:1ec:bdf::68 for threat intel correlation. 2. No immediate action required.",
                "frequency": 54,
                "source_ip": "127.0.0.1"
            }
        },
        "previous_hash": "7c15bffef9d9ee238350676c8d93196ed10d7615bff93906079fb7874c52625e",
        "hash": "3e2c949538eb56102f3ee09d508409771cbc0177aaf8bbfde87f2a699bef54a3"
    },
    {
        "index": 70,
        "timestamp": 1777702713.4771063,
        "data": {
            "type": "ALERT",
            "alert_id": "c3c9eaad-c4f8-4a40-8732-aa0944192cb1",
            "endpoint_id": "SachinChauhan",
            "timestamp": 1777702709.332097,
            "risk_level": "Low",
            "details": {
                "risk_level": "Low",
                "description": "Irregular Website/IP Usage",
                "destination_ip": "2620:1ec:bdf::68",
                "process_name": "Unknown",
                "metrics": "CPU: 37.6% | Mem: 86.9% | Net Tx: 0.0001MB/s",
                "root_cause": "Endpoint navigated to an IP that is not in its historical baseline.",
                "remediation": "1. Log IP 2620:1ec:bdf::68 for threat intel correlation. 2. No immediate action required.",
                "frequency": 55,
                "source_ip": "127.0.0.1"
            }
        },
        "previous_hash": "3e2c949538eb56102f3ee09d508409771cbc0177aaf8bbfde87f2a699bef54a3",
        "hash": "5b22a3aa2730946763f4927f8f702f9c5a4d42c049c8c4002cbc58d792a76be6"
    },
    {
        "index": 71,
        "timestamp": 1777702722.6516926,
        "data": {
            "type": "ALERT",
            "alert_id": "6581ea88-71fd-4d87-9427-9f73dd73166b",
            "endpoint_id": "SachinChauhan",
            "timestamp": 1777702718.5341537,
            "risk_level": "Low",
            "details": {
                "risk_level": "Low",
                "description": "Irregular Website/IP Usage",
                "destination_ip": "2620:1ec:bdf::68",
                "process_name": "Unknown",
                "metrics": "CPU: 31.9% | Mem: 87.0% | Net Tx: 0.0001MB/s",
                "root_cause": "Endpoint navigated to an IP that is not in its historical baseline.",
                "remediation": "1. Log IP 2620:1ec:bdf::68 for threat intel correlation. 2. No immediate action required.",
                "frequency": 56,
                "source_ip": "127.0.0.1"
            }
        },
        "previous_hash": "5b22a3aa2730946763f4927f8f702f9c5a4d42c049c8c4002cbc58d792a76be6",
        "hash": "8ec846ddd9a048259e3af67eb434413d8b39cb8d6e01a7d32bdba867eaed122c"
    },
    {
        "index": 72,
        "timestamp": 1777702731.8411677,
        "data": {
            "type": "ALERT",
            "alert_id": "04ea3e73-2feb-4f31-9817-0dbef6f650c4",
            "endpoint_id": "SachinChauhan",
            "timestamp": 1777702727.7108772,
            "risk_level": "Low",
            "details": {
                "risk_level": "Low",
                "description": "Irregular Website/IP Usage",
                "destination_ip": "2620:1ec:bdf::68",
                "process_name": "Unknown",
                "metrics": "CPU: 25.8% | Mem: 86.6% | Net Tx: 0.0001MB/s",
                "root_cause": "Endpoint navigated to an IP that is not in its historical baseline.",
                "remediation": "1. Log IP 2620:1ec:bdf::68 for threat intel correlation. 2. No immediate action required.",
                "frequency": 57,
                "source_ip": "127.0.0.1"
            }
        },
        "previous_hash": "8ec846ddd9a048259e3af67eb434413d8b39cb8d6e01a7d32bdba867eaed122c",
        "hash": "7f343ff6359b0349d02a297c5b2b1f1b26c99e910fc137b89ae32303010d7423"
    },
    {
        "index": 73,
        "timestamp": 1777702741.082998,
        "data": {
            "type": "ALERT",
            "alert_id": "6ecff3df-505f-48b4-a698-2a592284c591",
            "endpoint_id": "SachinChauhan",
            "timestamp": 1777702736.9148448,
            "risk_level": "Low",
            "details": {
                "risk_level": "Low",
                "description": "Irregular Website/IP Usage",
                "destination_ip": "2620:1ec:bdf::68",
                "process_name": "Unknown",
                "metrics": "CPU: 37.9% | Mem: 86.9% | Net Tx: 0.0011MB/s",
                "root_cause": "Endpoint navigated to an IP that is not in its historical baseline.",
                "remediation": "1. Log IP 2620:1ec:bdf::68 for threat intel correlation. 2. No immediate action required.",
                "frequency": 58,
                "source_ip": "127.0.0.1"
            }
        },
        "previous_hash": "7f343ff6359b0349d02a297c5b2b1f1b26c99e910fc137b89ae32303010d7423",
        "hash": "992c31501c856e58a779081346f1d2cf7b526bc052bd5479028f45df461caabb"
    },
    {
        "index": 74,
        "timestamp": 1777702750.2825327,
        "data": {
            "type": "ALERT",
            "alert_id": "84ef2c17-e33e-45b9-a1eb-cc2dffc6ac05",
            "endpoint_id": "SachinChauhan",
            "timestamp": 1777702746.165386,
            "risk_level": "Low",
            "details": {
                "risk_level": "Low",
                "description": "Irregular Website/IP Usage",
                "destination_ip": "2620:1ec:bdf::68",
                "process_name": "Unknown",
                "metrics": "CPU: 26.6% | Mem: 86.5% | Net Tx: 0.0006MB/s",
                "root_cause": "Endpoint navigated to an IP that is not in its historical baseline.",
                "remediation": "1. Log IP 2620:1ec:bdf::68 for threat intel correlation. 2. No immediate action required.",
                "frequency": 59,
                "source_ip": "127.0.0.1"
            }
        },
        "previous_hash": "992c31501c856e58a779081346f1d2cf7b526bc052bd5479028f45df461caabb",
        "hash": "d58b9aa1f8cab7f40990dbaaf913b0234336c5928f4d97a59ca1cf3df0ccfb01"
    },
    {
        "index": 75,
        "timestamp": 1777702759.470045,
        "data": {
            "type": "ALERT",
            "alert_id": "97ae6474-e7d0-41e7-a5bc-356ca5b10a19",
            "endpoint_id": "SachinChauhan",
            "timestamp": 1777702755.3230653,
            "risk_level": "Low",
            "details": {
                "risk_level": "Low",
                "description": "Irregular Website/IP Usage",
                "destination_ip": "2620:1ec:bdf::68",
                "process_name": "Unknown",
                "metrics": "CPU: 14.1% | Mem: 85.9% | Net Tx: 0.0011MB/s",
                "root_cause": "Endpoint navigated to an IP that is not in its historical baseline.",
                "remediation": "1. Log IP 2620:1ec:bdf::68 for threat intel correlation. 2. No immediate action required.",
                "frequency": 60,
                "source_ip": "127.0.0.1"
            }
        },
        "previous_hash": "d58b9aa1f8cab7f40990dbaaf913b0234336c5928f4d97a59ca1cf3df0ccfb01",
        "hash": "848c19d72b2c801674cd294a5e5fb2a9b9fd5bb3e6537eb53b3a83f104c1f746"
    },
    {
        "index": 76,
        "timestamp": 1777702768.6378574,
        "data": {
            "type": "ALERT",
            "alert_id": "f408e846-0a5a-414b-b57a-1f4b61049714",
            "endpoint_id": "SachinChauhan",
            "timestamp": 1777702764.5078425,
            "risk_level": "Low",
            "details": {
                "risk_level": "Low",
                "description": "Irregular Website/IP Usage",
                "destination_ip": "2620:1ec:bdf::68",
                "process_name": "Unknown",
                "metrics": "CPU: 11.3% | Mem: 85.9% | Net Tx: 0.0001MB/s",
                "root_cause": "Endpoint navigated to an IP that is not in its historical baseline.",
                "remediation": "1. Log IP 2620:1ec:bdf::68 for threat intel correlation. 2. No immediate action required.",
                "frequency": 61,
                "source_ip": "127.0.0.1"
            }
        },
        "previous_hash": "848c19d72b2c801674cd294a5e5fb2a9b9fd5bb3e6537eb53b3a83f104c1f746",
        "hash": "9eb6e2471c0c31768c505f0146ccb2992e0189b12a461eeb9827cd5927f15717"
    },
    {
        "index": 77,
        "timestamp": 1777702777.8137379,
        "data": {
            "type": "ALERT",
            "alert_id": "0a8253e0-7520-4dde-ad9a-7628f547820c",
            "endpoint_id": "SachinChauhan",
            "timestamp": 1777702773.6909204,
            "risk_level": "Low",
            "details": {
                "risk_level": "Low",
                "description": "Irregular Website/IP Usage",
                "destination_ip": "2620:1ec:bdf::68",
                "process_name": "Unknown",
                "metrics": "CPU: 12.3% | Mem: 86.0% | Net Tx: 0.0001MB/s",
                "root_cause": "Endpoint navigated to an IP that is not in its historical baseline.",
                "remediation": "1. Log IP 2620:1ec:bdf::68 for threat intel correlation. 2. No immediate action required.",
                "frequency": 62,
                "source_ip": "127.0.0.1"
            }
        },
        "previous_hash": "9eb6e2471c0c31768c505f0146ccb2992e0189b12a461eeb9827cd5927f15717",
        "hash": "807abaedfa50da06f59707354c07cefe560d2c49b05214bbe9bd77419e9090d8"
    },
    {
        "index": 78,
        "timestamp": 1777702801.2947013,
        "data": {
            "type": "ALERT",
            "alert_id": "279325ed-9e83-462f-baea-07601c1c67e3",
            "endpoint_id": "SachinChauhan",
            "timestamp": 1777702797.1671913,
            "risk_level": "Low",
            "details": {
                "risk_level": "Low",
                "description": "Irregular Website/IP Usage",
                "destination_ip": "20.189.173.10",
                "process_name": "Unknown",
                "metrics": "CPU: 20.3% | Mem: 86.4% | Net Tx: 0.0022MB/s",
                "root_cause": "Endpoint navigated to an IP that is not in its historical baseline.",
                "remediation": "1. Log IP 20.189.173.10 for threat intel correlation. 2. No immediate action required.",
                "frequency": 63,
                "source_ip": "127.0.0.1"
            }
        },
        "previous_hash": "807abaedfa50da06f59707354c07cefe560d2c49b05214bbe9bd77419e9090d8",
        "hash": "1c6b066f965183004001194b8c9e6753e2197f987f33e7f2ced4fa0c537f68e6"
    },
    {
        "index": 79,
        "timestamp": 1777702810.4769065,
        "data": {
            "type": "ALERT",
            "alert_id": "b1590777-9681-4251-a2ce-4539c69b0ec8",
            "endpoint_id": "SachinChauhan",
            "timestamp": 1777702806.337813,
            "risk_level": "Low",
            "details": {
                "risk_level": "Low",
                "description": "Minor Behavioral Deviation",
                "destination_ip": "N/A",
                "process_name": "N/A",
                "metrics": "CPU: 17.7% | Mem: 87.2% | Net Tx: 0.005MB/s",
                "root_cause": "General resource consumption pattern shifted slightly from the ML baseline.",
                "remediation": "1. No immediate action required. 2. Log for future behavioral auditing.",
                "frequency": 7,
                "source_ip": "127.0.0.1"
            }
        },
        "previous_hash": "1c6b066f965183004001194b8c9e6753e2197f987f33e7f2ced4fa0c537f68e6",
        "hash": "dd52b972e02e881e61e30dd8e3317ba7f0e6eab41906e86d7bbf14ad15f82405"
    },
    {
        "index": 80,
        "timestamp": 1777702812.4922082,
        "data": {
            "type": "ALERT",
            "alert_id": "10d8268f-2a21-46e5-ad12-dd8d5a12f012",
            "endpoint_id": "SachinChauhan",
            "timestamp": 1777702806.337813,
            "risk_level": "Low",
            "details": {
                "risk_level": "Low",
                "description": "Irregular Website/IP Usage",
                "destination_ip": "2607:6bc0::10",
                "process_name": "Unknown",
                "metrics": "CPU: 17.7% | Mem: 87.2% | Net Tx: 0.005MB/s",
                "root_cause": "Endpoint navigated to an IP that is not in its historical baseline.",
                "remediation": "1. Log IP 2607:6bc0::10 for threat intel correlation. 2. No immediate action required.",
                "frequency": 64,
                "source_ip": "127.0.0.1"
            }
        },
        "previous_hash": "dd52b972e02e881e61e30dd8e3317ba7f0e6eab41906e86d7bbf14ad15f82405",
        "hash": "c1c562f8f5362cfc504668d591badd823a806541c5bed0ccf39a1824bbe9852e"
    },
    {
        "index": 81,
        "timestamp": 1777702814.5311127,
        "data": {
            "type": "ALERT",
            "alert_id": "9138da21-3846-4ae6-844f-b8556f9cbd32",
            "endpoint_id": "SachinChauhan",
            "timestamp": 1777702806.337813,
            "risk_level": "Low",
            "details": {
                "risk_level": "Low",
                "description": "Irregular Website/IP Usage",
                "destination_ip": "20.189.173.10",
                "process_name": "Unknown",
                "metrics": "CPU: 17.7% | Mem: 87.2% | Net Tx: 0.005MB/s",
                "root_cause": "Endpoint navigated to an IP that is not in its historical baseline.",
                "remediation": "1. Log IP 20.189.173.10 for threat intel correlation. 2. No immediate action required.",
                "frequency": 65,
                "source_ip": "127.0.0.1"
            }
        },
        "previous_hash": "c1c562f8f5362cfc504668d591badd823a806541c5bed0ccf39a1824bbe9852e",
        "hash": "f8039e9c378d235df63a805f847bfe1d5bbb286315b4067fc82622a3c793dd54"
    },
    {
        "index": 82,
        "timestamp": 1777702823.7148542,
        "data": {
            "type": "ALERT",
            "alert_id": "caff9ca5-9c2e-48c5-9e69-d8cf91127360",
            "endpoint_id": "SachinChauhan",
            "timestamp": 1777702819.5551314,
            "risk_level": "Low",
            "details": {
                "risk_level": "Low",
                "description": "Irregular Website/IP Usage",
                "destination_ip": "2607:6bc0::10",
                "process_name": "Unknown",
                "metrics": "CPU: 15.2% | Mem: 87.3% | Net Tx: 0.0005MB/s",
                "root_cause": "Endpoint navigated to an IP that is not in its historical baseline.",
                "remediation": "1. Log IP 2607:6bc0::10 for threat intel correlation. 2. No immediate action required.",
                "frequency": 66,
                "source_ip": "127.0.0.1"
            }
        },
        "previous_hash": "f8039e9c378d235df63a805f847bfe1d5bbb286315b4067fc82622a3c793dd54",
        "hash": "7e263105db5f6f32b26ea018714df6d0a9e04f365ed13b40eedfdf2b47b309c9"
    },
    {
        "index": 83,
        "timestamp": 1777702825.743169,
        "data": {
            "type": "ALERT",
            "alert_id": "75fc9d8c-ed9d-485f-9344-9d7f456570d4",
            "endpoint_id": "SachinChauhan",
            "timestamp": 1777702819.5551314,
            "risk_level": "Low",
            "details": {
                "risk_level": "Low",
                "description": "Irregular Website/IP Usage",
                "destination_ip": "20.189.173.10",
                "process_name": "Unknown",
                "metrics": "CPU: 15.2% | Mem: 87.3% | Net Tx: 0.0005MB/s",
                "root_cause": "Endpoint navigated to an IP that is not in its historical baseline.",
                "remediation": "1. Log IP 20.189.173.10 for threat intel correlation. 2. No immediate action required.",
                "frequency": 67,
                "source_ip": "127.0.0.1"
            }
        },
        "previous_hash": "7e263105db5f6f32b26ea018714df6d0a9e04f365ed13b40eedfdf2b47b309c9",
        "hash": "da48a25de76da692f3f137cca19e0feb174fea766e94205dc5f5c8e5bcc52944"
    }
]